austrakka/__init__.py
austrakka/main.py
austrakka/components/__init__.py
austrakka/components/admin/__init__.py
austrakka/components/admin/message/__init__.py
austrakka/components/admin/message/funcs.py
austrakka/components/admin/message/dl/__init__.py
austrakka/components/admin/message/dl/funcs.py
austrakka/components/auth/__init__.py
austrakka/components/auth/enums.py
austrakka/components/auth/funcs.py
austrakka/components/auth/opts.py
austrakka/components/dashboard/__init__.py
austrakka/components/dashboard/project/__init__.py
austrakka/components/dashboard/project/funcs.py
austrakka/components/field/__init__.py
austrakka/components/field/funcs.py
austrakka/components/fieldtype/__init__.py
austrakka/components/fieldtype/funcs.py
austrakka/components/fieldtype/value/__init__.py
austrakka/components/fieldtype/value/funcs.py
austrakka/components/group/__init__.py
austrakka/components/group/funcs.py
austrakka/components/group/field/__init__.py
austrakka/components/group/field/funcs.py
austrakka/components/group/role/__init__.py
austrakka/components/group/role/funcs.py
austrakka/components/iam/__init__.py
austrakka/components/iam/privilege/__init__.py
austrakka/components/iam/privilege/funcs.py
austrakka/components/iam/role/__init__.py
austrakka/components/iam/role/funcs.py
austrakka/components/iam/role/definition/__init__.py
austrakka/components/iam/role/definition/funcs.py
austrakka/components/iam/scope/__init__.py
austrakka/components/iam/scope/funcs.py
austrakka/components/log/__init__.py
austrakka/components/log/funcs.py
austrakka/components/metadata/__init__.py
austrakka/components/metadata/funcs.py
austrakka/components/org/__init__.py
austrakka/components/org/funcs.py
austrakka/components/plot/__init__.py
austrakka/components/plot/funcs.py
austrakka/components/proforma/__init__.py
austrakka/components/proforma/funcs.py
austrakka/components/proforma/proforma_generation_utils.py
austrakka/components/project/__init__.py
austrakka/components/project/funcs.py
austrakka-0.77.0.dist-info/METADATA
austrakka-0.77.0.dist-info/WHEEL
austrakka-0.77.0.dist-info/entry_points.txt
austrakka-0.77.0.dist-info/top_level.txt
austrakka-0.77.0.dist-info/RECORD
